{
  "post_stream": {
    "posts": [
      {
        "id": 141236,
        "name": "",
        "username": "piratenpanda",
        "avatar_template": "/letter_avatar_proxy/v4/letter/p/9f8e36/{size}.png",
        "created_at": "2021-07-22T03:59:47.844Z",
        "cooked": "<p>Is there a reason why we can only choose shades of white for the avatar backgrounds? Also people without avatar now all look almost the same as the distinct difference is now only the smallest part of the circle namely the two initials. I am not sure if I am happy that new versions keep reducing accessibility for me</p>",
        "post_number": 1,
        "post_type": 1,
        "posts_count": 64,
        "updated_at": "2021-07-30T18:13:55.344Z",
        "reply_count": 0,
        "reply_to_post_number": null,
        "quote_count": 0,
        "incoming_link_count": 19,
        "reads": 184,
        "readers_count": 183,
        "score": 251.8,
        "yours": false,
        "topic_id": 35462,
        "topic_slug": "feedback-about-the-new-default-avatars-android-5-18-ios-5-17",
        "display_username": "",
        "primary_group_name": null,
        "flair_name": null,
        "flair_url": null,
        "flair_bg_color": null,
        "flair_color": null,
        "flair_group_id": null,
        "badges_granted": [],
        "version": 2,
        "can_edit": false,
        "can_delete": false,
        "can_recover": false,
        "can_see_hidden_post": false,
        "can_wiki": false,
        "link_counts": [
          {
            "url": "https://community.signalusers.org/t/beta-feedback-for-the-upcoming-android-5-18-release/35192/15",
            "internal": true,
            "reflection": true,
            "title": "Beta feedback for the upcoming Android 5.18 release",
            "clicks": 1
          },
          {
            "url": "https://community.signalusers.org/t/new-category-colours/46627/2",
            "internal": true,
            "reflection": true,
            "title": "New Category Colours",
            "clicks": 0
          }
        ],
        "read": true,
        "user_title": null,
        "bookmarked": false,
        "actions_summary": [
          {
            "id": 2,
            "count": 8
          }
        ],
        "moderator": false,
        "admin": false,
        "staff": false,
        "user_id": 359,
        "hidden": false,
        "trust_level": 2,
        "deleted_at": null,
        "user_deleted": false,
        "edit_reason": null,
        "can_view_edit_history": true,
        "wiki": false,
        "post_url": "/t/feedback-about-the-new-default-avatars-android-5-18-ios-5-17/35462/1",
        "can_accept_answer": false,
        "can_unaccept_answer": false,
        "accepted_answer": false,
        "topic_accepted_answer": null,
        "can_vote": false
      },
      {
        "id": 141356,
        "name": "Masqueey",
        "username": "Masqueey",
        "avatar_template": "/user_avatar/community.signalusers.org/masqueey/{size}/20782_2.png",
        "created_at": "2021-07-22T14:28:00.368Z",
        "cooked": "<p>I just want to say that I really like the new colours! It took a few seconds to adjust to their new brightness, but it is really well done! <img src=\"https://community.signalusers.org/images/emoji/apple/medal_sports.png?v=9\" title=\":medal_sports:\" class=\"emoji\" alt=\":medal_sports:\"></p>\n<p>I also like how the chat opening animation is coloured into the same colour as the chat and that auto colouring works the way it used to work again. And the alternative profile pictures are just the absolute cutest!</p>\n<p>As you might be able to tell, I’m really happy with this update, thank you for putting in all the hard work!</p>",
        "post_number": 2,
        "post_type": 1,
        "posts_count": 64,
        "updated_at": "2021-07-30T18:08:05.221Z",
        "reply_count": 0,
        "reply_to_post_number": null,
        "quote_count": 0,
        "incoming_link_count": 1,
        "reads": 160,
        "readers_count": 159,
        "score": 127.0,
        "yours": false,
        "topic_id": 35462,
        "topic_slug": "feedback-about-the-new-default-avatars-android-5-18-ios-5-17",
        "display_username": "Masqueey",
        "primary_group_name": null,
        "flair_name": null,
        "flair_url": null,
        "flair_bg_color": null,
        "flair_color": null,
        "flair_group_id": null,
        "badges_granted": [],
        "version": 1,
        "can_edit": false,
        "can_delete": false,
        "can_recover": false,
        "can_see_hidden_post": false,
        "can_wiki": false,
        "read": true,
        "user_title": null,
        "bookmarked": false,
        "actions_summary": [
          {
            "id": 2,
            "count": 4
          }
        ],
        "moderator": false,
        "admin": false,
        "staff": false,
        "user_id": 3291,
        "hidden": false,
        "trust_level": 2,
        "deleted_at": null,
        "user_deleted": false,
        "edit_reason": null,
        "can_view_edit_history": true,
        "wiki": false,
        "post_url": "/t/feedback-about-the-new-default-avatars-android-5-18-ios-5-17/35462/2",
        "can_accept_answer": false,
        "can_unaccept_answer": false,
        "accepted_answer": false,
        "topic_accepted_answer": null
      },
      {
        "id": 141442,
        "name": "",
        "username": "mrandr01d",
        "avatar_template": "/letter_avatar_proxy/v4/letter/m/f08c70/{size}.png",
        "created_at": "2021-07-23T01:30:57.991Z",
        "cooked": "<p>Not a fan of the pastel colors for the default initial avatars. Maybe all users should have a randomly assigned picture avatar, and they can change it if they want to? That would definitely encourage more people to set a custom avatar. The pastels also stand out funny in dark mode.</p>",
        "post_number": 3,
        "post_type": 1,
        "posts_count": 64,
        "updated_at": "2021-07-30T18:08:05.226Z",
        "reply_count": 0,
        "reply_to_post_number": null,
        "quote_count": 0,
        "incoming_link_count": 0,
        "reads": 163,
        "readers_count": 162,
        "score": 107.6,
        "yours": false,
        "topic_id": 35462,
        "topic_slug": "feedback-about-the-new-default-avatars-android-5-18-ios-5-17",
        "display_username": "",
        "primary_group_name": null,
        "flair_name": null,
        "flair_url": null,
        "flair_bg_color": null,
        "flair_color": null,
        "flair_group_id": null,
        "badges_granted": [],
        "version": 1,
        "can_edit": false,
        "can_delete": false,
        "can_recover": false,
        "can_see_hidden_post": false,
        "can_wiki": false,
        "read": true,
        "user_title": null,
        "bookmarked": false,
        "actions_summary": [
          {
            "id": 2,
            "count": 5
          }
        ],
        "moderator": false,
        "admin": false,
        "staff": false,
        "user_id": 1255,
        "hidden": false,
        "trust_level": 2,
        "deleted_at": null,
        "user_deleted": false,
        "edit_reason": null,
        "can_view_edit_history": true,
        "wiki": false,
        "post_url": "/t/feedback-about-the-new-default-avatars-android-5-18-ios-5-17/35462/3",
        "can_accept_answer": false,
        "can_unaccept_answer": false,
        "accepted_answer": false,
        "topic_accepted_answer": null
      },
      {
        "id": 141466,
        "name": null,
        "username": "anon61006462",
        "avatar_template": "/letter_avatar_proxy/v4/letter/a/3ab097/{size}.png",
        "created_at": "2021-07-23T10:00:14.738Z",
        "cooked": "<p>A bit of feedback on the new avatar color scheme, after some getting used to, it looks good with white theme,<br>\nbut the new avatar color scheme doesn’t really work with dark mode, especially at night, there should probably be a different color scheme for dark mode, something less distracting.</p>",
        "post_number": 4,
        "post_type": 1,
        "posts_count": 64,
        "updated_at": "2021-07-30T18:08:05.232Z",
        "reply_count": 1,
        "reply_to_post_number": null,
        "quote_count": 0,
        "incoming_link_count": 1,
        "reads": 152,
        "readers_count": 151,
        "score": 220.4,
        "yours": false,
        "topic_id": 35462,
        "topic_slug": "feedback-about-the-new-default-avatars-android-5-18-ios-5-17",
        "display_username": null,
        "primary_group_name": null,
        "flair_name": null,
        "flair_url": null,
        "flair_bg_color": null,
        "flair_color": null,
        "flair_group_id": null,
        "badges_granted": [],
        "version": 1,
        "can_edit": false,
        "can_delete": false,
        "can_recover": false,
        "can_see_hidden_post": false,
        "can_wiki": false,
        "read": true,
        "user_title": null,
        "bookmarked": false,
        "actions_summary": [
          {
            "id": 2,
            "count": 12
          }
        ],
        "moderator": false,
        "admin": false,
        "staff": false,
        "user_id": 11142,
        "hidden": false,
        "trust_level": 2,
        "deleted_at": null,
        "user_deleted": false,
        "edit_reason": null,
        "can_view_edit_history": true,
        "wiki": false,
        "post_url": "/t/feedback-about-the-new-default-avatars-android-5-18-ios-5-17/35462/4",
        "can_accept_answer": false,
        "can_unaccept_answer": false,
        "accepted_answer": false,
        "topic_accepted_answer": null
      },
      {
        "id": 141550,
        "name": "",
        "username": "low-key",
        "avatar_template": "/user_avatar/community.signalusers.org/low-key/{size}/28296_2.png",
        "created_at": "2021-07-23T18:32:44.308Z",
        "cooked": "<p>Hold on, what’s going on here? I don’t see a single one of these on my device. Where does one get these from and on a related note, I’m really loving the art style in these so is there somewhere one can more of these from? I don’t mind commissioning it if someone can point me towards the artist.</p>",
        "post_number": 5,
        "post_type": 1,
        "posts_count": 64,
        "updated_at": "2021-07-30T18:08:05.236Z",
        "reply_count": 1,
        "reply_to_post_number": null,
        "quote_count": 0,
        "incoming_link_count": 1,
        "reads": 139,
        "readers_count": 138,
        "score": 52.8,
        "yours": false,
        "topic_id": 35462,
        "topic_slug": "feedback-about-the-new-default-avatars-android-5-18-ios-5-17",
        "display_username": "",
        "primary_group_name": null,
        "flair_name": null,
        "flair_url": null,
        "flair_bg_color": null,
        "flair_color": null,
        "flair_group_id": null,
        "badges_granted": [],
        "version": 1,
        "can_edit": false,
        "can_delete": false,
        "can_recover": false,
        "can_see_hidden_post": false,
        "can_wiki": false,
        "read": true,
        "user_title": "",
        "bookmarked": false,
        "actions_summary": [
          {
            "id": 2,
            "count": 1
          }
        ],
        "moderator": false,
        "admin": false,
        "staff": false,
        "user_id": 289,
        "hidden": false,
        "trust_level": 2,
        "deleted_at": null,
        "user_deleted": false,
        "edit_reason": null,
        "can_view_edit_history": true,
        "wiki": false,
        "post_url": "/t/feedback-about-the-new-default-avatars-android-5-18-ios-5-17/35462/5",
        "can_accept_answer": false,
        "can_unaccept_answer": false,
        "accepted_answer": false,
        "topic_accepted_answer": null
      },
      {
        "id": 141551,
        "name": "Alex Hart",
        "username": "alex-signal",
        "avatar_template": "/user_avatar/community.signalusers.org/alex-signal/{size}/52314_2.png",
        "created_at": "2021-07-23T18:36:18.294Z",
        "cooked": "<p>All of the images were done by one of our designers <img src=\"https://community.signalusers.org/images/emoji/apple/slight_smile.png?v=9\" title=\":slight_smile:\" class=\"emoji\" alt=\":slight_smile:\"></p>\n<p>Do you have the latest beta installed? The screenshot shared is for group conversations.</p>",
        "post_number": 6,
        "post_type": 1,
        "posts_count": 64,
        "updated_at": "2021-07-30T18:08:05.240Z",
        "reply_count": 1,
        "reply_to_post_number": 5,
        "quote_count": 0,
        "incoming_link_count": 1,
        "reads": 144,
        "readers_count": 143,
        "score": 143.8,
        "yours": false,
        "topic_id": 35462,
        "topic_slug": "feedback-about-the-new-default-avatars-android-5-18-ios-5-17",
        "display_username": "Alex Hart",
        "primary_group_name": "signal_staff",
        "flair_name": "signal_staff",
        "flair_url": "/uploads/db3609/original/3X/0/6/064a72b694359c38b577ec83488ad474c77032dc.png",
        "flair_bg_color": "3B45FD",
        "flair_color": "",
        "flair_group_id": 46,
        "badges_granted": [],
        "version": 1,
        "can_edit": false,
        "can_delete": false,
        "can_recover": false,
        "can_see_hidden_post": false,
        "can_wiki": false,
        "read": true,
        "user_title": "Signal Staff",
        "title_is_group": true,
        "reply_to_user": {
          "id": 289,
          "username": "low-key",
          "name": "",
          "avatar_template": "/user_avatar/community.signalusers.org/low-key/{size}/28296_2.png"
        },
        "bookmarked": false,
        "actions_summary": [
          {
            "id": 2,
            "count": 5
          }
        ],
        "moderator": true,
        "admin": true,
        "staff": true,
        "user_id": 4053,
        "hidden": false,
        "trust_level": 4,
        "deleted_at": null,
        "user_deleted": false,
        "edit_reason": null,
        "can_view_edit_history": true,
        "wiki": false,
        "post_url": "/t/feedback-about-the-new-default-avatars-android-5-18-ios-5-17/35462/6",
        "can_accept_answer": false,
        "can_unaccept_answer": false,
        "accepted_answer": false,
        "topic_accepted_answer": null
      },
      {
        "id": 141552,
        "name": "",
        "username": "low-key",
        "avatar_template": "/user_avatar/community.signalusers.org/low-key/{size}/28296_2.png",
        "created_at": "2021-07-23T18:39:30.981Z",
        "cooked": "<p>Ah, I was only checking for my personal avatar.<br>\nCould you tell them they’ve done a wondrous job?<br>\nAnd is there anything at all one can do to get a giraffe added? Anything at all? <img src=\"https://community.signalusers.org/images/emoji/apple/pleading_face.png?v=9\" title=\":pleading_face:\" class=\"emoji\" alt=\":pleading_face:\"></p>",
        "post_number": 7,
        "post_type": 1,
        "posts_count": 64,
        "updated_at": "2021-07-30T18:08:05.243Z",
        "reply_count": 0,
        "reply_to_post_number": 6,
        "quote_count": 0,
        "incoming_link_count": 1,
        "reads": 146,
        "readers_count": 145,
        "score": 229.2,
        "yours": false,
        "topic_id": 35462,
        "topic_slug": "feedback-about-the-new-default-avatars-android-5-18-ios-5-17",
        "display_username": "",
        "primary_group_name": null,
        "flair_name": null,
        "flair_url": null,
        "flair_bg_color": null,
        "flair_color": null,
        "flair_group_id": null,
        "badges_granted": [],
        "version": 1,
        "can_edit": false,
        "can_delete": false,
        "can_recover": false,
        "can_see_hidden_post": false,
        "can_wiki": false,
        "read": true,
        "user_title": "",
        "reply_to_user": {
          "id": 4053,
          "username": "alex-signal",
          "name": "Alex Hart",
          "avatar_template": "/user_avatar/community.signalusers.org/alex-signal/{size}/52314_2.png"
        },
        "bookmarked": false,
        "actions_summary": [
          {
            "id": 2,
            "count": 9
          }
        ],
        "moderator": false,
        "admin": false,
        "staff": false,
        "user_id": 289,
        "hidden": false,
        "trust_level": 2,
        "deleted_at": null,
        "user_deleted": false,
        "edit_reason": null,
        "can_view_edit_history": true,
        "wiki": false,
        "post_url": "/t/feedback-about-the-new-default-avatars-android-5-18-ios-5-17/35462/7",
        "can_accept_answer": false,
        "can_unaccept_answer": false,
        "accepted_answer": false,
        "topic_accepted_answer": null
      },
      {
        "id": 141556,
        "name": "Navneet Vikram Tey",
        "username": "teynav",
        "avatar_template": "/letter_avatar_proxy/v4/letter/t/e99b99/{size}.png",
        "created_at": "2021-07-23T19:01:06.658Z",
        "cooked": "<p>Hi thanks for this 5.18 update, This has made group icon selection much better. Only issue? <strong>Limitation</strong></p>\n<details>\n<summary>\nSome of it kind of represent the other thing</summary>\n<p><div class=\"lightbox-wrapper\"><a class=\"lightbox\" href=\"https://community.signalusers.org/uploads/db3609/original/3X/1/9/1943932171cc8b00b940f8e4a6271047527334c1.jpeg\" data-download-href=\"https://community.signalusers.org/uploads/db3609/1943932171cc8b00b940f8e4a6271047527334c1\" title=\"Screenshot_20210724-002247_Signal (1)\"><img src=\"https://community.signalusers.org/uploads/db3609/optimized/3X/1/9/1943932171cc8b00b940f8e4a6271047527334c1_2_230x500.jpeg\" alt=\"Screenshot_20210724-002247_Signal (1)\" data-base62-sha1=\"3BuIkgJD12vrjkavpXBY3OHXuAV\" width=\"230\" height=\"500\" srcset=\"https://community.signalusers.org/uploads/db3609/optimized/3X/1/9/1943932171cc8b00b940f8e4a6271047527334c1_2_230x500.jpeg, https://community.signalusers.org/uploads/db3609/optimized/3X/1/9/1943932171cc8b00b940f8e4a6271047527334c1_2_345x750.jpeg 1.5x, https://community.signalusers.org/uploads/db3609/optimized/3X/1/9/1943932171cc8b00b940f8e4a6271047527334c1_2_460x1000.jpeg 2x\" data-small-upload=\"https://community.signalusers.org/uploads/db3609/optimized/3X/1/9/1943932171cc8b00b940f8e4a6271047527334c1_2_10x10.png\"><div class=\"meta\">\n<svg class=\"fa d-icon d-icon-far-image svg-icon\" aria-hidden=\"true\"><use xlink:href=\"#far-image\"></use></svg><span class=\"filename\">Screenshot_20210724-002247_Signal (1)</span><span class=\"informations\">1080×2340 237 KB</span><svg class=\"fa d-icon d-icon-discourse-expand svg-icon\" aria-hidden=\"true\"><use xlink:href=\"#discourse-expand\"></use></svg>\n</div></a></div></p>\n</details>\n<p>This is very good implementation and kudos to Signal Team for doing it, I would just suggest more Icons to represent plethora of group, I know it’s never enough.</p>\n<p>And the Irony is we can’t assign something “techy” to our techy-ish group :\"(</p>",
        "post_number": 8,
        "post_type": 1,
        "posts_count": 64,
        "updated_at": "2021-07-30T18:08:05.246Z",
        "reply_count": 0,
        "reply_to_post_number": null,
        "quote_count": 0,
        "incoming_link_count": 1,
        "reads": 142,
        "readers_count": 141,
        "score": 93.4,
        "yours": false,
        "topic_id": 35462,
        "topic_slug": "feedback-about-the-new-default-avatars-android-5-18-ios-5-17",
        "display_username": "Navneet Vikram Tey",
        "primary_group_name": null,
        "flair_name": null,
        "flair_url": null,
        "flair_bg_color": null,
        "flair_color": null,
        "flair_group_id": null,
        "badges_granted": [],
        "version": 1,
        "can_edit": false,
        "can_delete": false,
        "can_recover": false,
        "can_see_hidden_post": false,
        "can_wiki": false,
        "read": true,
        "user_title": "",
        "bookmarked": false,
        "actions_summary": [
          {
            "id": 2,
            "count": 4
          }
        ],
        "moderator": false,
        "admin": false,
        "staff": false,
        "user_id": 6363,
        "hidden": false,
        "trust_level": 2,
        "deleted_at": null,
        "user_deleted": false,
        "edit_reason": null,
        "can_view_edit_history": true,
        "wiki": false,
        "post_url": "/t/feedback-about-the-new-default-avatars-android-5-18-ios-5-17/35462/8",
        "can_accept_answer": false,
        "can_unaccept_answer": false,
        "accepted_answer": false,
        "topic_accepted_answer": null
      },
      {
        "id": 141562,
        "name": null,
        "username": "Signal.DE",
        "avatar_template": "/letter_avatar_proxy/v4/letter/s/13edae/{size}.png",
        "created_at": "2021-07-23T19:50:34.514Z",
        "cooked": "<p>Seeing the picture of teynav (above) with the sticker as avatar.</p>\n<p>Is there actual the possibility to select a sticker directly as avatar? Is that still to come?</p>\n<details>\n<summary>\nimage</summary>\n<p><div class=\"lightbox-wrapper\"><a class=\"lightbox\" href=\"https://community.signalusers.org/uploads/db3609/original/3X/9/5/9546ab9a41c7e6fdd8ec5909ab65755f24b818a6.png\" data-download-href=\"https://community.signalusers.org/uploads/db3609/9546ab9a41c7e6fdd8ec5909ab65755f24b818a6\" title=\"Screenshot_1627070953\"><img src=\"https://community.signalusers.org/uploads/db3609/optimized/3X/9/5/9546ab9a41c7e6fdd8ec5909ab65755f24b818a6_2_281x500.png\" alt=\"Screenshot_1627070953\" data-base62-sha1=\"liyyjTWOLZmFr0NtDhVLkbhQQlM\" width=\"281\" height=\"500\" srcset=\"https://community.signalusers.org/uploads/db3609/optimized/3X/9/5/9546ab9a41c7e6fdd8ec5909ab65755f24b818a6_2_281x500.png, https://community.signalusers.org/uploads/db3609/optimized/3X/9/5/9546ab9a41c7e6fdd8ec5909ab65755f24b818a6_2_421x750.png 1.5x, https://community.signalusers.org/uploads/db3609/optimized/3X/9/5/9546ab9a41c7e6fdd8ec5909ab65755f24b818a6_2_562x1000.png 2x\" data-small-upload=\"https://community.signalusers.org/uploads/db3609/optimized/3X/9/5/9546ab9a41c7e6fdd8ec5909ab65755f24b818a6_2_10x10.png\"><div class=\"meta\">\n<svg class=\"fa d-icon d-icon-far-image svg-icon\" aria-hidden=\"true\"><use xlink:href=\"#far-image\"></use></svg><span class=\"filename\">Screenshot_1627070953</span><span class=\"informations\">1080×1920 185 KB</span><svg class=\"fa d-icon d-icon-discourse-expand svg-icon\" aria-hidden=\"true\"><use xlink:href=\"#discourse-expand\"></use></svg>\n</div></a></div></p>\n</details>",
        "post_number": 9,
        "post_type": 1,
        "posts_count": 64,
        "updated_at": "2021-07-30T18:08:05.255Z",
        "reply_count": 0,
        "reply_to_post_number": null,
        "quote_count": 0,
        "incoming_link_count": 1,
        "reads": 132,
        "readers_count": 131,
        "score": 46.4,
        "yours": false,
        "topic_id": 35462,
        "topic_slug": "feedback-about-the-new-default-avatars-android-5-18-ios-5-17",
        "display_username": null,
        "primary_group_name": null,
        "flair_name": null,
        "flair_url": null,
        "flair_bg_color": null,
        "flair_color": null,
        "flair_group_id": null,
        "badges_granted": [],
        "version": 3,
        "can_edit": false,
        "can_delete": false,
        "can_recover": false,
        "can_see_hidden_post": false,
        "can_wiki": false,
        "read": true,
        "user_title": null,
        "bookmarked": false,
        "actions_summary": [
          {
            "id": 2,
            "count": 1
          }
        ],
        "moderator": false,
        "admin": false,
        "staff": false,
        "user_id": 2268,
        "hidden": false,
        "trust_level": 2,
        "deleted_at": null,
        "user_deleted": false,
        "edit_reason": null,
        "can_view_edit_history": true,
        "wiki": false,
        "post_url": "/t/feedback-about-the-new-default-avatars-android-5-18-ios-5-17/35462/9",
        "can_accept_answer": false,
        "can_unaccept_answer": false,
        "accepted_answer": false,
        "topic_accepted_answer": null
      },
      {
        "id": 141604,
        "name": "",
        "username": "intfeed",
        "avatar_template": "/letter_avatar_proxy/v4/letter/i/bc8723/{size}.png",
        "created_at": "2021-07-24T03:33:27.279Z",
        "cooked": "<p>Bright pastel colored avatar backgrounds clash with Dark Mode style.</p>",
        "post_number": 10,
        "post_type": 1,
        "posts_count": 64,
        "updated_at": "2021-07-30T18:08:05.260Z",
        "reply_count": 0,
        "reply_to_post_number": null,
        "quote_count": 0,
        "incoming_link_count": 0,
        "reads": 146,
        "readers_count": 145,
        "score": 104.2,
        "yours": false,
        "topic_id": 35462,
        "topic_slug": "feedback-about-the-new-default-avatars-android-5-18-ios-5-17",
        "display_username": "",
        "primary_group_name": null,
        "flair_name": null,
        "flair_url": null,
        "flair_bg_color": null,
        "flair_color": null,
        "flair_group_id": null,
        "badges_granted": [],
        "version": 1,
        "can_edit": false,
        "can_delete": false,
        "can_recover": false,
        "can_see_hidden_post": false,
        "can_wiki": false,
        "read": true,
        "user_title": null,
        "bookmarked": false,
        "actions_summary": [
          {
            "id": 2,
            "count": 5
          }
        ],
        "moderator": false,
        "admin": false,
        "staff": false,
        "user_id": 15648,
        "hidden": false,
        "trust_level": 2,
        "deleted_at": null,
        "user_deleted": false,
        "edit_reason": null,
        "can_view_edit_history": true,
        "wiki": false,
        "post_url": "/t/feedback-about-the-new-default-avatars-android-5-18-ios-5-17/35462/10",
        "can_accept_answer": false,
        "can_unaccept_answer": false,
        "accepted_answer": false,
        "topic_accepted_answer": null
      },
      {
        "id": 142568,
        "name": "",
        "username": "Sunspark",
        "avatar_template": "/letter_avatar_proxy/v4/letter/s/ba8739/{size}.png",
        "created_at": "2021-07-30T16:59:57.321Z",
        "cooked": "<p>I am a dark theme user. Today the Android app updated to 5.18.5 and one change I noticed right away is that the avatar circles (the ones without pictures) are now much lighter because this was done to make the light theme look better and now they glare out more with the dark theme which has a pure black background.</p>\n<p>The solution as I see it is to develop light and dark in parallel not make changes for light and have dark inherit them by default. A dark theme should not have lighter color bubbles. The previous version had darker colors for the avatar circles which was more appropriate for a dark theme.</p>\n<p>A compromise might be to have a “dim” theme like twitter has as one of its options, then there wouldn’t be quite so much contrast between pure black and and the new lighter circles.</p>",
        "post_number": 11,
        "post_type": 1,
        "posts_count": 64,
        "updated_at": "2021-07-30T18:08:32.297Z",
        "reply_count": 1,
        "reply_to_post_number": null,
        "quote_count": 0,
        "incoming_link_count": 1,
        "reads": 98,
        "readers_count": 97,
        "score": 89.6,
        "yours": false,
        "topic_id": 35462,
        "topic_slug": "feedback-about-the-new-default-avatars-android-5-18-ios-5-17",
        "display_username": "",
        "primary_group_name": null,
        "flair_name": null,
        "flair_url": null,
        "flair_bg_color": null,
        "flair_color": null,
        "flair_group_id": null,
        "badges_granted": [],
        "version": 1,
        "can_edit": false,
        "can_delete": false,
        "can_recover": false,
        "can_see_hidden_post": false,
        "can_wiki": false,
        "read": true,
        "user_title": null,
        "bookmarked": false,
        "actions_summary": [
          {
            "id": 2,
            "count": 4
          }
        ],
        "moderator": false,
        "admin": false,
        "staff": false,
        "user_id": 3488,
        "hidden": false,
        "trust_level": 2,
        "deleted_at": null,
        "user_deleted": false,
        "edit_reason": null,
        "can_view_edit_history": true,
        "wiki": false,
        "post_url": "/t/feedback-about-the-new-default-avatars-android-5-18-ios-5-17/35462/11",
        "can_accept_answer": false,
        "can_unaccept_answer": false,
        "accepted_answer": false,
        "topic_accepted_answer": null
      },
      {
        "id": 141142,
        "name": "Froiz",
        "username": "Froiz",
        "avatar_template": "/user_avatar/community.signalusers.org/froiz/{size}/10694_2.png",
        "created_at": "2021-07-21T14:38:46.521Z",
        "cooked": "<p>Maybe there’s an issue with the Dinossaur avatar. I set it, and I received a bunch of messages about my new avatar because it looks like a d***. Maybe is intended.</p>",
        "post_number": 12,
        "post_type": 1,
        "posts_count": 64,
        "updated_at": "2021-07-30T18:28:28.284Z",
        "reply_count": 0,
        "reply_to_post_number": null,
        "quote_count": 0,
        "incoming_link_count": 0,
        "reads": 152,
        "readers_count": 151,
        "score": 45.4,
        "yours": false,
        "topic_id": 35462,
        "topic_slug": "feedback-about-the-new-default-avatars-android-5-18-ios-5-17",
        "display_username": "Froiz",
        "primary_group_name": null,
        "flair_name": null,
        "flair_url": null,
        "flair_bg_color": null,
        "flair_color": null,
        "flair_group_id": null,
        "badges_granted": [],
        "version": 1,
        "can_edit": false,
        "can_delete": false,
        "can_recover": false,
        "can_see_hidden_post": false,
        "can_wiki": false,
        "link_counts": [
          {
            "url": "https://community.signalusers.org/t/beta-feedback-for-the-upcoming-ios-5-17-release/35127/18",
            "internal": true,
            "reflection": true,
            "title": "Beta feedback for the upcoming iOS 5.17 release",
            "clicks": 0
          }
        ],
        "read": true,
        "user_title": "",
        "bookmarked": false,
        "actions_summary": [
          {
            "id": 2,
            "count": 1
          }
        ],
        "moderator": false,
        "admin": false,
        "staff": false,
        "user_id": 7321,
        "hidden": false,
        "trust_level": 2,
        "deleted_at": null,
        "user_deleted": false,
        "edit_reason": null,
        "can_view_edit_history": true,
        "wiki": false,
        "post_url": "/t/feedback-about-the-new-default-avatars-android-5-18-ios-5-17/35462/12",
        "can_accept_answer": false,
        "can_unaccept_answer": false,
        "accepted_answer": false,
        "topic_accepted_answer": null
      },
      {
        "id": 141305,
        "name": "ch4tterb0x",
        "username": "chatterbox",
        "avatar_template": "/user_avatar/community.signalusers.org/chatterbox/{size}/15112_2.png",
        "created_at": "2021-07-22T09:40:39.653Z",
        "cooked": "<p>Should it be possible to choose a custom color for the background of avatars?</p>\n<p>If not, why not?</p>",
        "post_number": 13,
        "post_type": 1,
        "posts_count": 64,
        "updated_at": "2021-07-30T18:28:28.306Z",
        "reply_count": 2,
        "reply_to_post_number": null,
        "quote_count": 0,
        "incoming_link_count": 1,
        "reads": 145,
        "readers_count": 144,
        "score": 59.0,
        "yours": false,
        "topic_id": 35462,
        "topic_slug": "feedback-about-the-new-default-avatars-android-5-18-ios-5-17",
        "display_username": "ch4tterb0x",
        "primary_group_name": null,
        "flair_name": null,
        "flair_url": null,
        "flair_bg_color": null,
        "flair_color": null,
        "flair_group_id": null,
        "badges_granted": [],
        "version": 1,
        "can_edit": false,
        "can_delete": false,
        "can_recover": false,
        "can_see_hidden_post": false,
        "can_wiki": false,
        "read": true,
        "user_title": "",
        "bookmarked": false,
        "actions_summary": [
          {
            "id": 2,
            "count": 1
          }
        ],
        "moderator": false,
        "admin": false,
        "staff": false,
        "user_id": 11098,
        "hidden": false,
        "trust_level": 2,
        "deleted_at": null,
        "user_deleted": false,
        "edit_reason": null,
        "can_view_edit_history": true,
        "wiki": false,
        "post_url": "/t/feedback-about-the-new-default-avatars-android-5-18-ios-5-17/35462/13",
        "can_accept_answer": false,
        "can_unaccept_answer": false,
        "accepted_answer": false,
        "topic_accepted_answer": null
      },
      {
        "id": 141424,
        "name": null,
        "username": "anon27607767",
        "avatar_template": "/letter_avatar_proxy/v4/letter/a/b3f665/{size}.png",
        "created_at": "2021-07-22T20:39:21.419Z",
        "cooked": "<p>Yes it’s possible as described here.</p><aside class=\"quote\" data-post=\"3\" data-topic=\"35127\">\n  <div class=\"title\">\n    <div class=\"quote-controls\"></div>\n    <img loading=\"lazy\" alt=\"\" width=\"24\" height=\"24\" src=\"https://community.signalusers.org/user_avatar/community.signalusers.org/imperiopolis-signal/48/4226_2.png\" class=\"avatar\">\n    <a href=\"https://community.signalusers.org/t/beta-feedback-for-the-upcoming-ios-5-17-release/35127/3\">Beta feedback for the upcoming iOS 5.17 release</a> <a class=\"badge-category__wrapper \" href=\"/c/beta-feedback/ios-beta-feedback/98\"><span data-category-id=\"98\" style=\"--category-badge-color: #0088CC; --category-badge-text-color: #FFFFFF; --parent-category-badge-color: #0088CC;\" data-parent-category-id=\"25\" data-drop-close=\"true\" class=\"badge-category --has-parent\"><span class=\"badge-category__name\">iOS Beta Feedback</span></span></a>\n  </div>\n  <blockquote>\n    You can change the background color for the default images like the ghost. Tap on it a second time once the “pencil” icon is present.\n  </blockquote>\n</aside>\n",
        "post_number": 14,
        "post_type": 1,
        "posts_count": 64,
        "updated_at": "2021-07-30T18:28:28.317Z",
        "reply_count": 1,
        "reply_to_post_number": 13,
        "quote_count": 0,
        "incoming_link_count": 1,
        "reads": 142,
        "readers_count": 141,
        "score": 53.4,
        "yours": false,
        "topic_id": 35462,
        "topic_slug": "feedback-about-the-new-default-avatars-android-5-18-ios-5-17",
        "display_username": null,
        "primary_group_name": null,
        "flair_name": null,
        "flair_url": null,
        "flair_bg_color": null,
        "flair_color": null,
        "flair_group_id": null,
        "badges_granted": [],
        "version": 1,
        "can_edit": false,
        "can_delete": false,
        "can_recover": false,
        "can_see_hidden_post": false,
        "can_wiki": false,
        "link_counts": [
          {
            "url": "https://community.signalusers.org/t/beta-feedback-for-the-upcoming-ios-5-17-release/35127/3",
            "internal": true,
            "reflection": false,
            "title": "Beta feedback for the upcoming iOS 5.17 release",
            "clicks": 0
          }
        ],
        "read": true,
        "user_title": null,
        "reply_to_user": {
          "id": 11098,
          "username": "chatterbox",
          "name": "ch4tterb0x",
          "avatar_template": "/user_avatar/community.signalusers.org/chatterbox/{size}/15112_2.png"
        },
        "bookmarked": false,
        "actions_summary": [
          {
            "id": 2,
            "count": 1
          }
        ],
        "moderator": false,
        "admin": false,
        "staff": false,
        "user_id": 4313,
        "hidden": false,
        "trust_level": 2,
        "deleted_at": null,
        "user_deleted": false,
        "edit_reason": null,
        "can_view_edit_history": true,
        "wiki": false,
        "post_url": "/t/feedback-about-the-new-default-avatars-android-5-18-ios-5-17/35462/14",
        "can_accept_answer": false,
        "can_unaccept_answer": false,
        "accepted_answer": false,
        "topic_accepted_answer": null
      },
      {
        "id": 141427,
        "name": "ch4tterb0x",
        "username": "chatterbox",
        "avatar_template": "/user_avatar/community.signalusers.org/chatterbox/{size}/15112_2.png",
        "created_at": "2021-07-22T21:39:19.731Z",
        "cooked": "<p>I’m talking about choosing a custom color not one of the preselected.<br>\nI get the option to choose of 12 preselected colors, but I’m not able to choose a custom color.<br>\nAm I missing something?</p>\n<p>Sorry if this wasn’t clear.</p>",
        "post_number": 15,
        "post_type": 1,
        "posts_count": 64,
        "updated_at": "2021-07-30T18:28:28.327Z",
        "reply_count": 0,
        "reply_to_post_number": 14,
        "quote_count": 0,
        "incoming_link_count": 2,
        "reads": 143,
        "readers_count": 142,
        "score": 68.6,
        "yours": false,
        "topic_id": 35462,
        "topic_slug": "feedback-about-the-new-default-avatars-android-5-18-ios-5-17",
        "display_username": "ch4tterb0x",
        "primary_group_name": null,
        "flair_name": null,
        "flair_url": null,
        "flair_bg_color": null,
        "flair_color": null,
        "flair_group_id": null,
        "badges_granted": [],
        "version": 1,
        "can_edit": false,
        "can_delete": false,
        "can_recover": false,
        "can_see_hidden_post": false,
        "can_wiki": false,
        "read": true,
        "user_title": "",
        "reply_to_user": {
          "id": 4313,
          "username": "anon27607767",
          "name": null,
          "avatar_template": "/letter_avatar_proxy/v4/letter/a/b3f665/{size}.png"
        },
        "bookmarked": false,
        "actions_summary": [
          {
            "id": 2,
            "count": 2
          }
        ],
        "moderator": false,
        "admin": false,
        "staff": false,
        "user_id": 11098,
        "hidden": false,
        "trust_level": 2,
        "deleted_at": null,
        "user_deleted": false,
        "edit_reason": null,
        "can_view_edit_history": true,
        "wiki": false,
        "post_url": "/t/feedback-about-the-new-default-avatars-android-5-18-ios-5-17/35462/15",
        "can_accept_answer": false,
        "can_unaccept_answer": false,
        "accepted_answer": false,
        "topic_accepted_answer": null
      },
      {
        "id": 142586,
        "name": "",
        "username": "Blue42",
        "avatar_template": "/letter_avatar_proxy/v4/letter/b/d78d45/{size}.png",
        "created_at": "2021-07-30T18:44:32.716Z",
        "cooked": "<aside class=\"quote no-group\" data-username=\"chatterbox\" data-post=\"13\" data-topic=\"35462\" data-full=\"true\">\n<div class=\"title\">\n<div class=\"quote-controls\"></div>\n<img loading=\"lazy\" alt=\"\" width=\"24\" height=\"24\" src=\"https://community.signalusers.org/user_avatar/community.signalusers.org/chatterbox/48/15112_2.png\" class=\"avatar\"> chatterbox:</div>\n<blockquote>\n<p>Should it be possible to choose a custom color for the background of avatars?</p>\n<p>If not, why not?</p>\n</blockquote>\n</aside>\n<p>Not as of now,; idk</p>\n<details>\n<summary>\nMaybe because</summary>\n<p>You can’t select the foreground color, so background could clash <img src=\"https://community.signalusers.org/images/emoji/apple/person_shrugging.png?v=12\" title=\":person_shrugging:\" class=\"emoji\" alt=\":person_shrugging:\" loading=\"lazy\" width=\"20\" height=\"20\"></p>\n</details>",
        "post_number": 16,
        "post_type": 1,
        "posts_count": 64,
        "updated_at": "2021-07-30T18:44:32.716Z",
        "reply_count": 0,
        "reply_to_post_number": 13,
        "quote_count": 1,
        "incoming_link_count": 1,
        "reads": 96,
        "readers_count": 95,
        "score": 39.2,
        "yours": false,
        "topic_id": 35462,
        "topic_slug": "feedback-about-the-new-default-avatars-android-5-18-ios-5-17",
        "display_username": "",
        "primary_group_name": null,
        "flair_name": null,
        "flair_url": null,
        "flair_bg_color": null,
        "flair_color": null,
        "flair_group_id": null,
        "badges_granted": [],
        "version": 1,
        "can_edit": false,
        "can_delete": false,
        "can_recover": false,
        "can_see_hidden_post": false,
        "can_wiki": false,
        "read": true,
        "user_title": null,
        "bookmarked": false,
        "actions_summary": [
          {
            "id": 2,
            "count": 1
          }
        ],
        "moderator": false,
        "admin": false,
        "staff": false,
        "user_id": 14832,
        "hidden": false,
        "trust_level": 2,
        "deleted_at": null,
        "user_deleted": false,
        "edit_reason": null,
        "can_view_edit_history": true,
        "wiki": false,
        "post_url": "/t/feedback-about-the-new-default-avatars-android-5-18-ios-5-17/35462/16",
        "can_accept_answer": false,
        "can_unaccept_answer": false,
        "accepted_answer": false,
        "topic_accepted_answer": null
      },
      {
        "id": 142588,
        "name": "",
        "username": "Herohtar",
        "avatar_template": "/user_avatar/community.signalusers.org/herohtar/{size}/43780_2.png",
        "created_at": "2021-07-30T18:51:04.636Z",
        "cooked": "<p>The new avatar background options look out of place in dark mode, and they are all very similar. I suppose that’s because the intention is for the main difference to be the text color, but if you are using emoji as your “text” then you really don’t have a lot of background options.</p>",
        "post_number": 17,
        "post_type": 1,
        "posts_count": 64,
        "updated_at": "2021-07-30T18:51:33.786Z",
        "reply_count": 0,
        "reply_to_post_number": null,
        "quote_count": 0,
        "incoming_link_count": 1,
        "reads": 93,
        "readers_count": 92,
        "score": 98.6,
        "yours": false,
        "topic_id": 35462,
        "topic_slug": "feedback-about-the-new-default-avatars-android-5-18-ios-5-17",
        "display_username": "",
        "primary_group_name": "volunteer_moderators",
        "flair_name": "volunteer_moderators",
        "flair_url": "shield-halved",
        "flair_bg_color": "1d8663",
        "flair_color": "fff",
        "flair_group_id": 41,
        "badges_granted": [],
        "version": 1,
        "can_edit": false,
        "can_delete": false,
        "can_recover": false,
        "can_see_hidden_post": false,
        "can_wiki": false,
        "read": true,
        "user_title": "Volunteer Moderator",
        "title_is_group": true,
        "bookmarked": false,
        "actions_summary": [
          {
            "id": 2,
            "count": 5
          }
        ],
        "moderator": true,
        "admin": false,
        "staff": true,
        "user_id": 2521,
        "hidden": false,
        "trust_level": 4,
        "deleted_at": null,
        "user_deleted": false,
        "edit_reason": null,
        "can_view_edit_history": true,
        "wiki": false,
        "post_url": "/t/feedback-about-the-new-default-avatars-android-5-18-ios-5-17/35462/17",
        "can_accept_answer": false,
        "can_unaccept_answer": false,
        "accepted_answer": false,
        "topic_accepted_answer": null
      },
      {
        "id": 142591,
        "name": "link ✦",
        "username": "awaitlink",
        "avatar_template": "/user_avatar/community.signalusers.org/awaitlink/{size}/48975_2.png",
        "created_at": "2021-07-30T18:58:23.197Z",
        "cooked": "<p>To clarify the nature of this topic: to organize the feedback about this change (lighter default avatars + avatar editor with text or new default images as options) a little bit, I’ve merged posts about it into a single topic. That is why some posts above aren’t exactly in chronological order.</p>\n<p>Some feedback can’t be merged as easily because the posts are not entirely about the change itself. These posts are listed below for completeness:</p>\n<ul>\n<li><a href=\"https://community.signalusers.org/t/beta-feedback-for-the-upcoming-ios-5-17-release/35127/8\" class=\"inline-onebox\">Beta feedback for the upcoming iOS 5.17 release - #8 by M00nD3v</a></li>\n<li><a href=\"https://community.signalusers.org/t/beta-feedback-for-the-upcoming-ios-5-17-release/35127/12\" class=\"inline-onebox\">Beta feedback for the upcoming iOS 5.17 release - #12 by MindlessDistance</a></li>\n<li><a href=\"https://community.signalusers.org/t/beta-feedback-for-the-upcoming-android-5-18-release/35192/16\" class=\"inline-onebox\">Beta feedback for the upcoming Android 5.18 release - #16 by ponytail</a></li>\n<li><a href=\"https://community.signalusers.org/t/beta-feedback-for-the-upcoming-android-5-18-release/35192/59\" class=\"inline-onebox\">Beta feedback for the upcoming Android 5.18 release - #59 by Signal.DE</a></li>\n<li><a href=\"https://community.signalusers.org/t/beta-feedback-for-the-upcoming-android-5-18-release/35192/176\" class=\"inline-onebox\">Beta feedback for the upcoming Android 5.18 release - #176 by p4nci</a></li>\n</ul>\n<hr>\n<aside class=\"quote no-group\" data-username=\"anon61006462\" data-post=\"4\" data-topic=\"35462\">\n<div class=\"title\">\n<div class=\"quote-controls\"></div>\n<img alt=\"\" width=\"24\" height=\"24\" src=\"https://community.signalusers.org/letter_avatar_proxy/v4/letter/a/3ab097/48.png\" class=\"avatar\"> anon61006462:</div>\n<blockquote>\n<p>there should probably be a different color scheme for dark mode, something less distracting</p>\n</blockquote>\n</aside>\n<aside class=\"quote no-group\" data-username=\"Sunspark\" data-post=\"11\" data-topic=\"35462\">\n<div class=\"title\">\n<div class=\"quote-controls\"></div>\n<img alt=\"\" width=\"24\" height=\"24\" src=\"https://community.signalusers.org/letter_avatar_proxy/v4/letter/s/ba8739/48.png\" class=\"avatar\"> Sunspark:</div>\n<blockquote>\n<p>A dark theme should not have lighter color bubbles. The previous version had darker colors for the avatar circles which was more appropriate for a dark theme.</p>\n</blockquote>\n</aside>\n<p>Having a separate “dark” variant would indeed work for the default avatars, which are automatically generated on the device.</p>\n<p>The slight issue, however, is that, for the avatars that the user sets (for their profile and for groups), if they use the avatar creator/editor for making an avatar with a default graphic or with text, it would currently just set it as an image, as explained in the following post:</p>\n<aside class=\"quote quote-modified\" data-post=\"46\" data-topic=\"35192\">\n  <div class=\"title\">\n    <div class=\"quote-controls\"></div>\n    <img alt=\"\" width=\"24\" height=\"24\" src=\"https://community.signalusers.org/user_avatar/community.signalusers.org/alex-signal/48/52314_2.png\" class=\"avatar\">\n    <a href=\"https://community.signalusers.org/t/beta-feedback-for-the-upcoming-android-5-18-release/35192/46\">Beta feedback for the upcoming Android 5.18 release</a> <a class=\"badge-category__wrapper \" href=\"/c/beta-feedback/android-beta-feedback/97\"><span data-category-id=\"97\" style=\"--category-badge-color: #0088CC; --category-badge-text-color: #FFFFFF; --parent-category-badge-color: #0088CC;\" data-parent-category-id=\"25\" data-drop-close=\"true\" class=\"badge-category --has-parent\"><span class=\"badge-category__name\">Android Beta Feedback</span></span></a>\n  </div>\n  <blockquote>\n    This is impossible (or at least not practical). When you save the icon, we convert it into a jpeg that can be uploaded. Nothing outside of the avatar picker sees your selection as a vector and background color, it sees an image. When you enter the screen again and we grab your “current” avatar, we see an image and thus no selection is made. \nWe could render a jpeg of each preview and compare it to the one you’ve set, but this is going to have a lot of false negatives and be super CPU intensive …\n  </blockquote>\n</aside>\n\n<p>So users may be confused why some default avatars correctly appear according to their theme, while other “default” ones (which really are regular profile pictures set by the user) do not (even more so if they are “text” avatars just like the “real” default avatars).</p>\n<p>Solving this “slight issue” would likely require storing the “color” and “text / image option” separately as part of the user’s Signal Profile, which has some challenges such as:</p>\n<ul>\n<li>Compatibility with older Signal versions (temporary);</li>\n<li>Ensuring users do not have their avatar unexpectedly change (if the default ones are ever changed, removed, or new ones are added or if the color palette/selections are changed).</li>\n</ul>",
        "post_number": 18,
        "post_type": 1,
        "posts_count": 64,
        "updated_at": "2021-07-30T19:01:49.243Z",
        "reply_count": 1,
        "reply_to_post_number": null,
        "quote_count": 2,
        "incoming_link_count": 1,
        "reads": 98,
        "readers_count": 97,
        "score": 74.6,
        "yours": false,
        "topic_id": 35462,
        "topic_slug": "feedback-about-the-new-default-avatars-android-5-18-ios-5-17",
        "display_username": "link ✦",
        "primary_group_name": "volunteer_moderators",
        "flair_name": "volunteer_moderators",
        "flair_url": "shield-halved",
        "flair_bg_color": "1d8663",
        "flair_color": "fff",
        "flair_group_id": 41,
        "badges_granted": [],
        "version": 1,
        "can_edit": false,
        "can_delete": false,
        "can_recover": false,
        "can_see_hidden_post": false,
        "can_wiki": false,
        "link_counts": [
          {
            "url": "https://community.signalusers.org/t/beta-feedback-for-the-upcoming-android-5-18-release/35192/176",
            "internal": true,
            "reflection": false,
            "title": "Beta feedback for the upcoming Android 5.18 release",
            "clicks": 3
          },
          {
            "url": "https://community.signalusers.org/t/beta-feedback-for-the-upcoming-ios-5-17-release/35127/8",
            "internal": true,
            "reflection": false,
            "title": "Beta feedback for the upcoming iOS 5.17 release",
            "clicks": 3
          },
          {
            "url": "https://community.signalusers.org/t/beta-feedback-for-the-upcoming-android-5-18-release/35192/16",
            "internal": true,
            "reflection": false,
            "title": "Beta feedback for the upcoming Android 5.18 release",
            "clicks": 2
          },
          {
            "url": "https://community.signalusers.org/t/beta-feedback-for-the-upcoming-android-5-18-release/35192/59",
            "internal": true,
            "reflection": false,
            "title": "Beta feedback for the upcoming Android 5.18 release",
            "clicks": 2
          },
          {
            "url": "https://community.signalusers.org/t/beta-feedback-for-the-upcoming-ios-5-17-release/35127/12",
            "internal": true,
            "reflection": false,
            "title": "Beta feedback for the upcoming iOS 5.17 release",
            "clicks": 2
          },
          {
            "url": "https://community.signalusers.org/t/beta-feedback-for-the-upcoming-android-5-18-release/35192/46",
            "internal": true,
            "reflection": false,
            "title": "Beta feedback for the upcoming Android 5.18 release",
            "clicks": 0
          }
        ],
        "read": true,
        "user_title": "Volunteer Moderator",
        "title_is_group": true,
        "bookmarked": false,
        "actions_summary": [
          {
            "id": 2,
            "count": 1
          }
        ],
        "moderator": true,
        "admin": false,
        "staff": true,
        "user_id": 3070,
        "hidden": false,
        "trust_level": 4,
        "deleted_at": null,
        "user_deleted": false,
        "edit_reason": null,
        "can_view_edit_history": true,
        "wiki": false,
        "post_url": "/t/feedback-about-the-new-default-avatars-android-5-18-ios-5-17/35462/18",
        "can_accept_answer": false,
        "can_unaccept_answer": false,
        "accepted_answer": false,
        "topic_accepted_answer": null
      },
      {
        "id": 142592,
        "name": null,
        "username": "anon61006462",
        "avatar_template": "/letter_avatar_proxy/v4/letter/a/3ab097/{size}.png",
        "created_at": "2021-07-30T19:18:34.532Z",
        "cooked": "<aside class=\"quote group-volunteer_moderators\" data-username=\"awaitlink\" data-post=\"18\" data-topic=\"35462\">\n<div class=\"title\">\n<div class=\"quote-controls\"></div>\n<img loading=\"lazy\" alt=\"\" width=\"24\" height=\"24\" src=\"https://community.signalusers.org/user_avatar/community.signalusers.org/awaitlink/48/48975_2.png\" class=\"avatar\"> awaitlink:</div>\n<blockquote>\n<p>The slight issue, however, is that, for the avatars that the user sets (for their profile and for groups), if they use the avatar creator/editor for making an avatar with a default graphic or with text, it would currently just set it as an image, as explained in the following post:</p>\n</blockquote>\n</aside>\n<p>Yep, this all makes sense.</p>\n<p>so considering I don’t really think we need this feature,</p>\n<p>maybe drop the ability to change the background color, keep the text and the sticker like avatars, (perhaps add some more that work better with dark mode for people to choose)</p>\n<p>and give the option of changing the text color instead of the background, let the background be determined automatically depending on the displaying client’s color theme.</p>\n<p>it would require some predefined text colors that work on both dark and light backgrounds.</p>\n<p>it’s just a two minute thought… feel free to pick it apart <img src=\"https://community.signalusers.org/images/emoji/apple/laughing.png?v=12\" title=\":laughing:\" class=\"emoji\" alt=\":laughing:\" loading=\"lazy\" width=\"20\" height=\"20\"></p>\n<p>I should probably just open a feature request for users to have the in-app option of setting their own avatars for their contacts, without using the picture in Android’s contacts app.</p>\n<p>if there isn’t such a request already.</p>",
        "post_number": 19,
        "post_type": 1,
        "posts_count": 64,
        "updated_at": "2021-07-30T19:18:34.532Z",
        "reply_count": 0,
        "reply_to_post_number": 18,
        "quote_count": 1,
        "incoming_link_count": 1,
        "reads": 98,
        "readers_count": 97,
        "score": 39.6,
        "yours": false,
        "topic_id": 35462,
        "topic_slug": "feedback-about-the-new-default-avatars-android-5-18-ios-5-17",
        "display_username": null,
        "primary_group_name": null,
        "flair_name": null,
        "flair_url": null,
        "flair_bg_color": null,
        "flair_color": null,
        "flair_group_id": null,
        "badges_granted": [],
        "version": 1,
        "can_edit": false,
        "can_delete": false,
        "can_recover": false,
        "can_see_hidden_post": false,
        "can_wiki": false,
        "read": true,
        "user_title": null,
        "bookmarked": false,
        "actions_summary": [
          {
            "id": 2,
            "count": 1
          }
        ],
        "moderator": false,
        "admin": false,
        "staff": false,
        "user_id": 11142,
        "hidden": false,
        "trust_level": 2,
        "deleted_at": null,
        "user_deleted": false,
        "edit_reason": null,
        "can_view_edit_history": true,
        "wiki": false,
        "post_url": "/t/feedback-about-the-new-default-avatars-android-5-18-ios-5-17/35462/19",
        "can_accept_answer": false,
        "can_unaccept_answer": false,
        "accepted_answer": false,
        "topic_accepted_answer": null
      },
      {
        "id": 142611,
        "name": "",
        "username": "Pheasant",
        "avatar_template": "/letter_avatar_proxy/v4/letter/p/8baadc/{size}.png",
        "created_at": "2021-07-30T22:42:54.061Z",
        "cooked": "<p>The contrast between the black background of dark theme is too much for me. It’s better in the light theme, but the letters and backgrounds are harder to tell apart at a glance than the old way in either theme.</p>\n<p>It probably doesn’t matter much for people with lots of contacts that have chosen avatars, but only about 5 of my 30 or so Signal contacts have set one (to say nothing of all the SMS only contacts who can’t), so my conversation list is just a sea of bright but difficult to distinguish icons.</p>\n<p>Of course, what I really want is to match the icon color to the chat color, but associating people with particular colors is naughty.</p>\n<p>I’m at the point where I’m just going to set images for all my contacts so I can get something decent. But those don’t sync with the desktop version, do they? Is there any way to change them there?</p>",
        "post_number": 20,
        "post_type": 1,
        "posts_count": 64,
        "updated_at": "2021-07-30T22:42:54.061Z",
        "reply_count": 2,
        "reply_to_post_number": null,
        "quote_count": 0,
        "incoming_link_count": 0,
        "reads": 95,
        "readers_count": 94,
        "score": 44.0,
        "yours": false,
        "topic_id": 35462,
        "topic_slug": "feedback-about-the-new-default-avatars-android-5-18-ios-5-17",
        "display_username": "",
        "primary_group_name": null,
        "flair_name": null,
        "flair_url": null,
        "flair_bg_color": null,
        "flair_color": null,
        "flair_group_id": null,
        "badges_granted": [],
        "version": 1,
        "can_edit": false,
        "can_delete": false,
        "can_recover": false,
        "can_see_hidden_post": false,
        "can_wiki": false,
        "read": true,
        "user_title": null,
        "bookmarked": false,
        "actions_summary": [
          {
            "id": 2,
            "count": 1
          }
        ],
        "moderator": false,
        "admin": false,
        "staff": false,
        "user_id": 1447,
        "hidden": false,
        "trust_level": 2,
        "deleted_at": null,
        "user_deleted": false,
        "edit_reason": null,
        "can_view_edit_history": true,
        "wiki": false,
        "post_url": "/t/feedback-about-the-new-default-avatars-android-5-18-ios-5-17/35462/20",
        "can_accept_answer": false,
        "can_unaccept_answer": false,
        "accepted_answer": false,
        "topic_accepted_answer": null
      }
    ],
    "stream": [
      141236,
      141356,
      141442,
      141466,
      141550,
      141551,
      141552,
      141556,
      141562,
      141604,
      142568,
      141142,
      141305,
      141424,
      141427,
      142586,
      142588,
      142591,
      142592,
      142611,
      142631,
      142654,
      142655,
      142657,
      142661,
      142663,
      142694,
      142696,
      142698,
      142707,
      142711,
      142718,
      142720,
      142726,
      142729,
      142731,
      142732,
      142734,
      142736,
      142737,
      142738,
      142750,
      142745,
      142839,
      143059,
      143062,
      143204,
      143208,
      143220,
      143221,
      143226,
      143249,
      143260,
      143264,
      143271,
      143343,
      143585,
      143874,
      143952,
      144115,
      144130,
      144333,
      144492,
      267029
    ]
  },
  "timeline_lookup": [
    [
      1,
      1669
    ],
    [
      2,
      1668
    ],
    [
      4,
      1667
    ],
    [
      11,
      1660
    ],
    [
      12,
      1669
    ],
    [
      13,
      1668
    ],
    [
      16,
      1660
    ],
    [
      22,
      1659
    ],
    [
      44,
      1658
    ],
    [
      45,
      1656
    ],
    [
      47,
      1655
    ],
    [
      52,
      1654
    ],
    [
      57,
      1652
    ],
    [
      58,
      1650
    ],
    [
      59,
      1649
    ],
    [
      60,
      1648
    ],
    [
      62,
      1646
    ],
    [
      64,
      293
    ]
  ],
  "tags_descriptions": {},
  "fancy_title": "Feedback about the new default avatars (Android 5.18, iOS 5.17)",
  "id": 35462,
  "title": "Feedback about the new default avatars (Android 5.18, iOS 5.17)",
  "posts_count": 64,
  "created_at": "2021-07-22T03:59:47.844Z",
  "views": 1465,
  "reply_count": 33,
  "like_count": 165,
  "last_posted_at": "2025-04-27T11:18:08.329Z",
  "visible": true,
  "closed": false,
  "archived": false,
  "has_summary": true,
  "archetype": "regular",
  "slug": "feedback-about-the-new-default-avatars-android-5-18-ios-5-17",
  "category_id": 28,
  "word_count": 7870,
  "deleted_at": null,
  "user_id": 359,
  "featured_link": null,
  "pinned_globally": false,
  "pinned_at": null,
  "pinned_until": null,
  "image_url": null,
  "slow_mode_seconds": 0,
  "draft": null,
  "draft_key": "topic_35462",
  "draft_sequence": null,
  "unpinned": null,
  "pinned": false,
  "current_post_number": 1,
  "highest_post_number": 65,
  "deleted_by": null,
  "actions_summary": [
    {
      "id": 4,
      "count": 0,
      "hidden": false,
      "can_act": false
    },
    {
      "id": 8,
      "count": 0,
      "hidden": false,
      "can_act": false
    },
    {
      "id": 10,
      "count": 0,
      "hidden": false,
      "can_act": false
    },
    {
      "id": 7,
      "count": 0,
      "hidden": false,
      "can_act": false
    }
  ],
  "chunk_size": 20,
  "bookmarked": false,
  "topic_timer": null,
  "message_bus_last_id": 0,
  "participant_count": 27,
  "show_read_indicator": false,
  "thumbnails": null,
  "slow_mode_enabled_until": null,
  "can_vote": false,
  "vote_count": 0,
  "user_voted": false,
  "discourse_zendesk_plugin_zendesk_id": null,
  "discourse_zendesk_plugin_zendesk_url": "https://your-url.zendesk.com/agent/tickets/",
  "details": {
    "can_edit": false,
    "notification_level": 1,
    "participants": [
      {
        "id": 2170,
        "username": "TeeJay82",
        "name": "",
        "avatar_template": "/user_avatar/community.signalusers.org/teejay82/{size}/1806_2.png",
        "post_count": 13,
        "primary_group_name": null,
        "flair_name": null,
        "flair_url": null,
        "flair_color": null,
        "flair_bg_color": null,
        "flair_group_id": null,
        "trust_level": 2
      },
      {
        "id": 7651,
        "username": "TransMK2",
        "name": "Trans Mk2",
        "avatar_template": "/user_avatar/community.signalusers.org/transmk2/{size}/22850_2.png",
        "post_count": 6,
        "primary_group_name": null,
        "flair_name": null,
        "flair_url": null,
        "flair_color": null,
        "flair_bg_color": null,
        "flair_group_id": null,
        "trust_level": 1
      },
      {
        "id": 2521,
        "username": "Herohtar",
        "name": "",
        "avatar_template": "/user_avatar/community.signalusers.org/herohtar/{size}/43780_2.png",
        "post_count": 5,
        "primary_group_name": "volunteer_moderators",
        "flair_name": "volunteer_moderators",
        "flair_url": "shield-halved",
        "flair_color": "fff",
        "flair_bg_color": "1d8663",
        "flair_group_id": 41,
        "moderator": true,
        "trust_level": 4
      },
      {
        "id": 14832,
        "username": "Blue42",
        "name": "",
        "avatar_template": "/letter_avatar_proxy/v4/letter/b/d78d45/{size}.png",
        "post_count": 5,
        "primary_group_name": null,
        "flair_name": null,
        "flair_url": null,
        "flair_color": null,
        "flair_bg_color": null,
        "flair_group_id": null,
        "trust_level": 2
      },
      {
        "id": 4696,
        "username": "newuser",
        "name": null,
        "avatar_template": "/letter_avatar_proxy/v4/letter/n/3e96dc/{size}.png",
        "post_count": 3,
        "primary_group_name": null,
        "flair_name": null,
        "flair_url": null,
        "flair_color": null,
        "flair_bg_color": null,
        "flair_group_id": null,
        "trust_level": 2
      },
      {
        "id": 11098,
        "username": "chatterbox",
        "name": "ch4tterb0x",
        "avatar_template": "/user_avatar/community.signalusers.org/chatterbox/{size}/15112_2.png",
        "post_count": 3,
        "primary_group_name": null,
        "flair_name": null,
        "flair_url": null,
        "flair_color": null,
        "flair_bg_color": null,
        "flair_group_id": null,
        "trust_level": 2
      },
      {
        "id": 2474,
        "username": "stevenwalton",
        "name": "Steven",
        "avatar_template": "/user_avatar/community.signalusers.org/stevenwalton/{size}/2130_2.png",
        "post_count": 3,
        "primary_group_name": null,
        "flair_name": null,
        "flair_url": null,
        "flair_color": null,
        "flair_bg_color": null,
        "flair_group_id": null,
        "trust_level": 2
      },
      {
        "id": 11142,
        "username": "anon61006462",
        "name": null,
        "avatar_template": "/letter_avatar_proxy/v4/letter/a/3ab097/{size}.png",
        "post_count": 3,
        "primary_group_name": null,
        "flair_name": null,
        "flair_url": null,
        "flair_color": null,
        "flair_bg_color": null,
        "flair_group_id": null,
        "trust_level": 2
      },
      {
        "id": 289,
        "username": "low-key",
        "name": "",
        "avatar_template": "/user_avatar/community.signalusers.org/low-key/{size}/28296_2.png",
        "post_count": 2,
        "primary_group_name": null,
        "flair_name": null,
        "flair_url": null,
        "flair_color": null,
        "flair_bg_color": null,
        "flair_group_id": null,
        "trust_level": 2
      },
      {
        "id": 1447,
        "username": "Pheasant",
        "name": "",
        "avatar_template": "/letter_avatar_proxy/v4/letter/p/8baadc/{size}.png",
        "post_count": 2,
        "primary_group_name": null,
        "flair_name": null,
        "flair_url": null,
        "flair_color": null,
        "flair_bg_color": null,
        "flair_group_id": null,
        "trust_level": 2
      },
      {
        "id": 3070,
        "username": "awaitlink",
        "name": "link ✦",
        "avatar_template": "/user_avatar/community.signalusers.org/awaitlink/{size}/48975_2.png",
        "post_count": 2,
        "primary_group_name": "volunteer_moderators",
        "flair_name": "volunteer_moderators",
        "flair_url": "shield-halved",
        "flair_color": "fff",
        "flair_bg_color": "1d8663",
        "flair_group_id": 41,
        "moderator": true,
        "trust_level": 4
      },
      {
        "id": 3488,
        "username": "Sunspark",
        "name": "",
        "avatar_template": "/letter_avatar_proxy/v4/letter/s/ba8739/{size}.png",
        "post_count": 2,
        "primary_group_name": null,
        "flair_name": null,
        "flair_url": null,
        "flair_color": null,
        "flair_bg_color": null,
        "flair_group_id": null,
        "trust_level": 2
      },
      {
        "id": 4313,
        "username": "anon27607767",
        "name": null,
        "avatar_template": "/letter_avatar_proxy/v4/letter/a/b3f665/{size}.png",
        "post_count": 1,
        "primary_group_name": null,
        "flair_name": null,
        "flair_url": null,
        "flair_color": null,
        "flair_bg_color": null,
        "flair_group_id": null,
        "trust_level": 2
      },
      {
        "id": 4053,
        "username": "alex-signal",
        "name": "Alex Hart",
        "avatar_template": "/user_avatar/community.signalusers.org/alex-signal/{size}/52314_2.png",
        "post_count": 1,
        "primary_group_name": "signal_staff",
        "flair_name": "signal_staff",
        "flair_url": "/uploads/db3609/original/3X/0/6/064a72b694359c38b577ec83488ad474c77032dc.png",
        "flair_color": "",
        "flair_bg_color": "3B45FD",
        "flair_group_id": 46,
        "admin": true,
        "moderator": true,
        "trust_level": 4
      },
      {
        "id": 5895,
        "username": "Undercover",
        "name": "",
        "avatar_template": "/letter_avatar_proxy/v4/letter/u/ea5d25/{size}.png",
        "post_count": 1,
        "primary_group_name": null,
        "flair_name": null,
        "flair_url": null,
        "flair_color": null,
        "flair_bg_color": null,
        "flair_group_id": null,
        "trust_level": 2
      },
      {
        "id": 6363,
        "username": "teynav",
        "name": "Navneet Vikram Tey",
        "avatar_template": "/letter_avatar_proxy/v4/letter/t/e99b99/{size}.png",
        "post_count": 1,
        "primary_group_name": null,
        "flair_name": null,
        "flair_url": null,
        "flair_color": null,
        "flair_bg_color": null,
        "flair_group_id": null,
        "trust_level": 2
      },
      {
        "id": 6431,
        "username": "pm_me_your_privkeys",
        "name": null,
        "avatar_template": "/letter_avatar_proxy/v4/letter/p/ecd19e/{size}.png",
        "post_count": 1,
        "primary_group_name": null,
        "flair_name": null,
        "flair_url": null,
        "flair_color": null,
        "flair_bg_color": null,
        "flair_group_id": null,
        "trust_level": 1
      },
      {
        "id": 7321,
        "username": "Froiz",
        "name": "Froiz",
        "avatar_template": "/user_avatar/community.signalusers.org/froiz/{size}/10694_2.png",
        "post_count": 1,
        "primary_group_name": null,
        "flair_name": null,
        "flair_url": null,
        "flair_color": null,
        "flair_bg_color": null,
        "flair_group_id": null,
        "trust_level": 2
      },
      {
        "id": 3291,
        "username": "Masqueey",
        "name": "Masqueey",
        "avatar_template": "/user_avatar/community.signalusers.org/masqueey/{size}/20782_2.png",
        "post_count": 1,
        "primary_group_name": null,
        "flair_name": null,
        "flair_url": null,
        "flair_color": null,
        "flair_bg_color": null,
        "flair_group_id": null,
        "trust_level": 2
      },
      {
        "id": 8198,
        "username": "marcode",
        "name": "marcode",
        "avatar_template": "/user_avatar/community.signalusers.org/marcode/{size}/15586_2.png",
        "post_count": 1,
        "primary_group_name": null,
        "flair_name": null,
        "flair_url": null,
        "flair_color": null,
        "flair_bg_color": null,
        "flair_group_id": null,
        "trust_level": 2
      },
      {
        "id": 2268,
        "username": "Signal.DE",
        "name": null,
        "avatar_template": "/letter_avatar_proxy/v4/letter/s/13edae/{size}.png",
        "post_count": 1,
        "primary_group_name": null,
        "flair_name": null,
        "flair_url": null,
        "flair_color": null,
        "flair_bg_color": null,
        "flair_group_id": null,
        "trust_level": 2
      },
      {
        "id": 1255,
        "username": "mrandr01d",
        "name": "",
        "avatar_template": "/letter_avatar_proxy/v4/letter/m/f08c70/{size}.png",
        "post_count": 1,
        "primary_group_name": null,
        "flair_name": null,
        "flair_url": null,
        "flair_color": null,
        "flair_bg_color": null,
        "flair_group_id": null,
        "trust_level": 2
      },
      {
        "id": 12350,
        "username": "Brind_it_on",
        "name": "Brind On",
        "avatar_template": "/user_avatar/community.signalusers.org/brind_it_on/{size}/16100_2.png",
        "post_count": 1,
        "primary_group_name": null,
        "flair_name": null,
        "flair_url": null,
        "flair_color": null,
        "flair_bg_color": null,
        "flair_group_id": null,
        "trust_level": 2
      },
      {
        "id": 359,
        "username": "piratenpanda",
        "name": "",
        "avatar_template": "/letter_avatar_proxy/v4/letter/p/9f8e36/{size}.png",
        "post_count": 1,
        "primary_group_name": null,
        "flair_name": null,
        "flair_url": null,
        "flair_color": null,
        "flair_bg_color": null,
        "flair_group_id": null,
        "trust_level": 2
      }
    ],
    "created_by": {
      "id": 359,
      "username": "piratenpanda",
      "name": "",
      "avatar_template": "/letter_avatar_proxy/v4/letter/p/9f8e36/{size}.png"
    },
    "last_poster": {
      "id": 18089,
      "username": "Aku-Stable",
      "name": "",
      "avatar_template": "/user_avatar/community.signalusers.org/aku-stable/{size}/25198_2.png"
    },
    "links": [
      {
        "url": "https://community.signalusers.org/t/beta-feedback-for-the-upcoming-android-7-41-release/68760/15",
        "title": "Beta feedback for the upcoming Android 7.41 release",
        "internal": true,
        "attachment": false,
        "reflection": false,
        "clicks": 4,
        "user_id": 18089,
        "domain": "community.signalusers.org",
        "root_domain": "signalusers.org"
      },
      {
        "url": "https://community.signalusers.org/t/beta-feedback-for-the-upcoming-android-5-18-release/35192/176",
        "title": "Beta feedback for the upcoming Android 5.18 release",
        "internal": true,
        "attachment": false,
        "reflection": false,
        "clicks": 3,
        "user_id": 3070,
        "domain": "community.signalusers.org",
        "root_domain": "signalusers.org"
      },
      {
        "url": "https://community.signalusers.org/t/beta-feedback-for-the-upcoming-ios-5-17-release/35127/29",
        "title": "Beta feedback for the upcoming iOS 5.17 release",
        "internal": true,
        "attachment": false,
        "reflection": true,
        "clicks": 3,
        "user_id": 3070,
        "domain": "community.signalusers.org",
        "root_domain": "signalusers.org"
      },
      {
        "url": "https://community.signalusers.org/t/beta-feedback-for-the-upcoming-ios-5-17-release/35127/8",
        "title": "Beta feedback for the upcoming iOS 5.17 release",
        "internal": true,
        "attachment": false,
        "reflection": false,
        "clicks": 3,
        "user_id": 3070,
        "domain": "community.signalusers.org",
        "root_domain": "signalusers.org"
      },
      {
        "url": "https://www.w3.org/TR/WCAG21/#dfn-relative-luminance",
        "title": "Web Content Accessibility Guidelines (WCAG) 2.1",
        "internal": false,
        "attachment": false,
        "reflection": false,
        "clicks": 2,
        "user_id": 14832,
        "domain": "www.w3.org",
        "root_domain": "w3.org"
      },
      {
        "url": "https://community.signalusers.org/t/beta-feedback-for-the-upcoming-android-5-18-release/35192/16",
        "title": "Beta feedback for the upcoming Android 5.18 release",
        "internal": true,
        "attachment": false,
        "reflection": false,
        "clicks": 2,
        "user_id": 3070,
        "domain": "community.signalusers.org",
        "root_domain": "signalusers.org"
      },
      {
        "url": "https://community.signalusers.org/t/beta-feedback-for-the-upcoming-android-5-18-release/35192/59",
        "title": "Beta feedback for the upcoming Android 5.18 release",
        "internal": true,
        "attachment": false,
        "reflection": false,
        "clicks": 2,
        "user_id": 3070,
        "domain": "community.signalusers.org",
        "root_domain": "signalusers.org"
      },
      {
        "url": "https://community.signalusers.org/t/beta-feedback-for-the-upcoming-ios-5-17-release/35127/12",
        "title": "Beta feedback for the upcoming iOS 5.17 release",
        "internal": true,
        "attachment": false,
        "reflection": false,
        "clicks": 2,
        "user_id": 3070,
        "domain": "community.signalusers.org",
        "root_domain": "signalusers.org"
      },
      {
        "url": "https://community.signalusers.org/t/beta-feedback-for-the-upcoming-android-5-18-release/35192/15",
        "title": "Beta feedback for the upcoming Android 5.18 release",
        "internal": true,
        "attachment": false,
        "reflection": true,
        "clicks": 1,
        "user_id": 3070,
        "domain": "community.signalusers.org",
        "root_domain": "signalusers.org"
      }
    ]
  },
  "bookmarks": []
}